reddit_comment_harvester/__init__.py
reddit_comment_harvester/fetch.py
reddit_comment_harvester/models.py
reddit_comment_harvester/parser.py
reddit_comment_harvester/scrape.py
reddit_comment_harvester/scraper.py
reddit_comment_harvester-0.1.7.dist-info/licenses/LICENSE
reddit_comment_harvester-0.1.7.dist-info/METADATA
reddit_comment_harvester-0.1.7.dist-info/WHEEL
reddit_comment_harvester-0.1.7.dist-info/top_level.txt
reddit_comment_harvester-0.1.7.dist-info/RECORD
