Metadata-Version: 2.4
Name: reddit-comment-harvester
Version: 0.1.7
Summary: Extract Reddit threads and comment trees for research and analysis
Author: Wiley
License: MIT
Project-URL: Homepage, https://github.com/wlyastn/reddit-comment-harvester
Project-URL: Documentation, https://github.com/wlyastn/reddit-comment-harvester/blob/main/README.md
Project-URL: Repository, https://github.com/wlyastn/reddit-comment-harvester
Project-URL: Issues, https://github.com/wlyastn/reddit-comment-harvester/issues
Keywords: reddit,comments,research,data-analysis,scraper
Classifier: Development Status :: 3 - Alpha
Classifier: Intended Audience :: Developers
Classifier: Intended Audience :: Science/Research
Classifier: Programming Language :: Python :: 3
Classifier: Programming Language :: Python :: 3.9
Classifier: Programming Language :: Python :: 3.10
Classifier: Programming Language :: Python :: 3.11
Classifier: Programming Language :: Python :: 3.12
Classifier: Programming Language :: Python :: 3.13
Classifier: Topic :: Software Development :: Libraries :: Python Modules
Classifier: Topic :: Internet :: WWW/HTTP
Classifier: Topic :: Scientific/Engineering
Classifier: License :: OSI Approved :: MIT License
Requires-Python: >=3.9
License-File: LICENSE
Requires-Dist: requests>=2.31.0
Dynamic: license-file
